examples/__init__.py
examples/stringwrap.py
examples/typecheck.py
paramdec/__init__.py
paramdec/paramdec.py
paramdec-2.1.0.dist-info/DESCRIPTION.rst
paramdec-2.1.0.dist-info/METADATA
paramdec-2.1.0.dist-info/RECORD
paramdec-2.1.0.dist-info/WHEEL
paramdec-2.1.0.dist-info/metadata.json
paramdec-2.1.0.dist-info/top_level.txt
