Metadata-Version: 2.0
Name: paramdec
Version: 2.1.0
Summary: A convenient way to create parametrized decorators.
Home-page: https://github.com/Suenweek/paramdec
Author: Roman Novatorov <suenweek@protonmail.com>
Author-email: suenweek@protonmail.com
License: GPLv3
Keywords: development parametrized decorator
Platform: UNKNOWN
Classifier: Development Status :: 4 - Beta
Classifier: Intended Audience :: Developers
Classifier: Topic :: Software Development :: Libraries :: Python Modules
Classifier: License :: OSI Approved :: GNU Lesser General Public License v3 (LGPLv3)
Classifier: Programming Language :: Python :: 2
Classifier: Programming Language :: Python :: 3
